pyhessian/__init__.py
pyhessian/client.py
pyhessian/data_types.py
pyhessian/encoder.py
pyhessian/parser.py
pyhessian/protocol.py
pyhessian/utils.py
python_hessian-1.2.0.dist-info/LICENSE
python_hessian-1.2.0.dist-info/METADATA
python_hessian-1.2.0.dist-info/WHEEL
python_hessian-1.2.0.dist-info/top_level.txt
python_hessian-1.2.0.dist-info/zip-safe
python_hessian-1.2.0.dist-info/RECORD
